pygeoip/__init__.py
pygeoip/const.py
pygeoip/timezone.py
pygeoip/util.py
pygeoip-0.3.1.dist-info/DESCRIPTION.rst
pygeoip-0.3.1.dist-info/METADATA
pygeoip-0.3.1.dist-info/pydist.json
pygeoip-0.3.1.dist-info/RECORD
pygeoip-0.3.1.dist-info/top_level.txt
pygeoip-0.3.1.dist-info/WHEEL
